pylint_to_ruff/__init__.py
pylint_to_ruff/__main__.py
pylint_to_ruff/cli.py
pylint_to_ruff/pylint.py
pylint_to_ruff/ruff.py
pylint_to_ruff/ruff_aliases.py
pylint_to_ruff-0.3.0.dist-info/METADATA
pylint_to_ruff-0.3.0.dist-info/WHEEL
pylint_to_ruff-0.3.0.dist-info/entry_points.txt
pylint_to_ruff-0.3.0.dist-info/licenses/LICENSE
pylint_to_ruff-0.3.0.dist-info/RECORD
