Metadata-Version: 2.1
Name: pylint-to-ruff
Version: 0.3.0
Summary: Introspect a Pylint configuration and convert it to Ruff
Project-URL: Documentation, https://github.com/akx/pylint-to-ruff#readme
Project-URL: Issues, https://github.com/akx/pylint-to-ruff/issues
Project-URL: Source, https://github.com/akx/pylint-to-ruff
Author-email: Aarni Koskela <akx@iki.fi>
License-Expression: MIT
License-File: LICENSE
Keywords: lint,pylint,ruff
Classifier: Development Status :: 4 - Beta
Classifier: Programming Language :: Python
Classifier: Programming Language :: Python :: 3.9
Classifier: Programming Language :: Python :: 3.10
Classifier: Programming Language :: Python :: 3.11
Classifier: Programming Language :: Python :: Implementation :: CPython
Classifier: Programming Language :: Python :: Implementation :: PyPy
Requires-Python: >=3.9
Provides-Extra: dev
Requires-Dist: pytest-cov; extra == 'dev'
Requires-Dist: pytest>=7.0; extra == 'dev'
